flutils/__init__.py
flutils/__init__.pyi
flutils/cmdutils.py
flutils/decorators.py
flutils/moduleutils.py
flutils/namedtupleutils.py
flutils/objutils.py
flutils/packages.py
flutils/pathutils.py
flutils/py.typed
flutils/strutils.py
flutils/txtutils.py
flutils/validators.py
flutils/codecs/__init__.py
flutils/codecs/b64.py
flutils/codecs/raw_utf8_escape.py
flutils/setuputils/__init__.py
flutils/setuputils/cfg.py
flutils/setuputils/cmd.py
flutils-0.7.dist-info/LICENSE
flutils-0.7.dist-info/METADATA
flutils-0.7.dist-info/WHEEL
flutils-0.7.dist-info/top_level.txt
flutils-0.7.dist-info/RECORD
